{
  "slug": "lv-019",
  "number": 19,
  "title": "Basilisk Loop",
  "mode": "form",
  "kind": "custom",
  "mdx": "prompt.mdx",
  "saltHex": "b8061d963bb7261426f74a525b59e48e",
  "userHashHex": "43c2043de0bacfb385581a7d635197301298cd28f7af51f498977c9890e09674",
  "passHashHex": "d42548c968c0ec0062cf3982718b090dec1af776486d3f590cabfb1e088f0e06",
  "hintsConsole": [
    "XOR every 64th entry to find the loop seed.",
    "Construct a De Bruijn sequence of order 4."
  ],
  "hintsSource": [
    "loop-research.pdf outlines the algorithm.",
    "sequence-helper.py verifies your sequence."
  ],
  "theme": {
    "className": "level-basilisk-loop",
    "cssVars": {
      "--accent": "#a9ff8c",
      "--bg": "#041407"
    }
  }
}
